pywinsparkle-1.6.0.data/purelib/pywinsparkle/__init__.py
pywinsparkle-1.6.0.data/purelib/pywinsparkle/pywinsparkle.py
pywinsparkle-1.6.0.data/purelib/pywinsparkle/libs/x64/WinSparkle.dll
pywinsparkle-1.6.0.data/purelib/pywinsparkle/libs/x86/WinSparkle.dll
pywinsparkle-1.6.0.dist-info/LICENSE.txt
pywinsparkle-1.6.0.dist-info/METADATA
pywinsparkle-1.6.0.dist-info/WHEEL
pywinsparkle-1.6.0.dist-info/top_level.txt
pywinsparkle-1.6.0.dist-info/RECORD
