Metadata-Version: 2.1
Name: pywinsparkle
Version: 1.6.0
Summary: A python wrapper for the winsparkle project
Home-page: https://github.com/dyer234/pywinsparkle
Author: Daniel Dyer
Author-email: dyer234@gmail.com
License: MIT
Keywords: sparkle winsparkle windows update
Platform: UNKNOWN
Classifier: Development Status :: 5 - Production/Stable
Classifier: Intended Audience :: Developers
Classifier: Topic :: Software Development
Classifier: License :: OSI Approved :: MIT License
Classifier: Programming Language :: Python :: 2.7
Classifier: Programming Language :: Python :: 3
